Rumba-0.9.data/scripts/rumba-access
rumba/__init__.py
rumba/_version.py
rumba/log.py
rumba/model.py
rumba/multiprocess.py
rumba/recpoisson.py
rumba/ssh_support.py
rumba/storyboard.py
rumba/utils.py
rumba/elements/__init__.py
rumba/elements/experimentation.py
rumba/elements/topology.py
rumba/executors/__init__.py
rumba/executors/docker.py
rumba/executors/local.py
rumba/executors/ssh.py
rumba/prototypes/__init__.py
rumba/prototypes/enroll.py
rumba/prototypes/irati.py
rumba/prototypes/irati_templates.py
rumba/prototypes/ouroboros.py
rumba/prototypes/rlite.py
rumba/testbeds/__init__.py
rumba/testbeds/dockertb.py
rumba/testbeds/emulab.py
rumba/testbeds/jfed.py
rumba/testbeds/local.py
rumba/testbeds/qemu.py
Rumba-0.9.dist-info/AUTHORS.txt
Rumba-0.9.dist-info/LICENSE.txt
Rumba-0.9.dist-info/METADATA
Rumba-0.9.dist-info/WHEEL
Rumba-0.9.dist-info/top_level.txt
Rumba-0.9.dist-info/RECORD
